revisit_notebook_widget/__init__.py
revisit_notebook_widget/sampleconfig.json
revisit_notebook_widget/sampleconfig2.json
revisit_notebook_widget/sampleconfig3.json
revisit_notebook_widget/revisit/__init__.py
revisit_notebook_widget/revisit/models.py
revisit_notebook_widget/revisit/revisit.py
revisit_notebook_widget/static/widget.css
revisit_notebook_widget/static/widget.js
revisit_notebook_widget-0.0.2.dist-info/METADATA
revisit_notebook_widget-0.0.2.dist-info/WHEEL
revisit_notebook_widget-0.0.2.dist-info/RECORD
