Metadata-Version: 2.4
Name: revisit_notebook_widget
Version: 0.0.2
Requires-Dist: anywidget
Requires-Dist: ipykernel>=6.29.5
Requires-Dist: pydantic>=2.10.5
Provides-Extra: dev
Requires-Dist: jupyterlab; extra == 'dev'
Requires-Dist: watchfiles; extra == 'dev'
